.coveragerc
LICENSE
MANIFEST.in
README.md
setup.py
tox.ini
drf_pdf/__init__.py
drf_pdf/exceptions.py
drf_pdf/renderer.py
drf_pdf/response.py
drf_pdf.egg-info/PKG-INFO
drf_pdf.egg-info/SOURCES.txt
drf_pdf.egg-info/dependency_links.txt
drf_pdf.egg-info/requires.txt
drf_pdf.egg-info/top_level.txt
tests/__init__.py
tests/test_renderer.py
tests/test_response.py
tests/test_run.py