Metadata-Version: 1.1
Name: drf-pdf
Version: 0.2.0
Summary: A simple PDF renderer for Django Rest Framework
Home-page: https://github.com/drgarcia1986/drf-pdf
Author: Diego Garcia
Author-email: drgarcia1986@gmail.com
License: UNKNOWN
Keywords: django djangorestframework render response pdf
Platform: UNKNOWN
Classifier: Framework :: Django
Classifier: Intended Audience :: Developers
Classifier: License :: OSI Approved :: MIT License
Classifier: Operating System :: OS Independent
Classifier: Programming Language :: Python :: 2
Classifier: Programming Language :: Python :: 3
